{
  "$schema": "https://ui.shadcn.com/schema/registry-item.json",
  "name": "skin-terminal",
  "title": "Terminal / TUI skin",
  "description": "Terminal concept skin: phosphor green-on-black, monospace, [ bracketed ] buttons, CRT scanlines. A CSS overlay scoped to [data-skin=\"terminal\"].",
  "files": [
    {
      "path": "app/skins/terminal.css",
      "content": "/* ==========================================================================\n   SKIN: Terminal / TUI   ·   [data-skin=\"terminal\"]\n   Phosphor green-on-black, monospace everything, hairline green borders,\n   [ bracketed ] buttons, faint CRT scanlines, a blinking caret. Pure CSS.\n   ========================================================================== */\n\n:root[data-skin=\"terminal\"] {\n  --app-font-sans: \"JetBrains Mono\", \"Cascadia Mono\", \"DejaVu Sans Mono\", ui-monospace, \"Courier New\", monospace;\n  --app-font-heading: var(--app-font-sans);\n  --app-font-mono: var(--app-font-sans);\n  --app-font-size: 13px;\n\n  --radius: 0px;\n\n  --background: #0a120c;\n  --foreground: #2bff66;\n  --card: #0c1810;\n  --card-foreground: #2bff66;\n  --popover: #0c1810;\n  --popover-foreground: #2bff66;\n  --primary: #2bff66;\n  --primary-foreground: #04140a;\n  --secondary: #0c1810;\n  --secondary-foreground: #2bff66;\n  --muted: #0c1810;\n  --muted-foreground: #36a85a;\n  --accent: #2bff66;\n  --accent-foreground: #04140a;\n  --destructive: #ff5f56;\n  --border: #1f6f3a;\n  --input: #1f6f3a;\n  --ring: #2bff66;\n  --chart-1: #2bff66;\n  --chart-2: #17a843;\n  --chart-3: #7dff9f;\n  --chart-4: #0c6b27;\n  --chart-5: #b6ffca;\n  --sidebar: #0c1810;\n  --sidebar-foreground: #2bff66;\n  --sidebar-accent: #2bff66;\n  --sidebar-accent-foreground: #04140a;\n  --sidebar-border: #1f6f3a;\n}\n\n[data-skin=\"terminal\"] body {\n  background: #060a07;\n  color: #2bff66;\n}\n[data-skin=\"terminal\"] ::selection { background: #2bff66; color: #04140a; }\n[data-skin=\"terminal\"] * { text-shadow: 0 0 1px rgba(43, 255, 102, 0.35); }\n\n/* faint CRT scanlines over everything */\n[data-skin=\"terminal\"] body::before {\n  content: \"\";\n  position: fixed;\n  inset: 0;\n  pointer-events: none;\n  z-index: 9999;\n  background: repeating-linear-gradient(\n    to bottom,\n    rgba(0, 0, 0, 0) 0px,\n    rgba(0, 0, 0, 0) 2px,\n    rgba(0, 0, 0, 0.22) 3px,\n    rgba(0, 0, 0, 0.22) 3px\n  );\n  mix-blend-mode: multiply;\n}\n\n@keyframes term-blink { 0%, 49% { opacity: 1; } 50%, 100% { opacity: 0; } }\n\n/* ---- Shell -------------------------------------------------------------- */\n[data-skin=\"terminal\"] .app { max-width: 980px; }\n[data-skin=\"terminal\"] .app-bar {\n  background: #0a120c;\n  border: 1px solid var(--border);\n  border-radius: 0;\n  box-shadow: 0 0 12px rgba(43, 255, 102, 0.12);\n  backdrop-filter: none;\n}\n[data-skin=\"terminal\"] .app-brand::before { content: \"$ \"; color: #36a85a; }\n[data-skin=\"terminal\"] .app-bar-controls label::before { content: \"--\"; opacity: 0.6; }\n\n[data-skin=\"terminal\"] .app-nav-inner {\n  border: 1px solid var(--border);\n  border-radius: 0;\n  background: #0a120c;\n}\n[data-skin=\"terminal\"] .app-nav-title { color: #36a85a; }\n[data-skin=\"terminal\"] .app-nav-title::before { content: \"~/\"; }\n[data-skin=\"terminal\"] .app-nav a { border-radius: 0; }\n[data-skin=\"terminal\"] .app-nav a::before { content: \"› \"; color: #1f6f3a; }\n[data-skin=\"terminal\"] .app-nav a:hover { background: #2bff66; color: #04140a; }\n[data-skin=\"terminal\"] .app-nav a:hover::before { color: #04140a; }\n\n[data-skin=\"terminal\"] .hero {\n  border: 1px solid var(--border);\n  border-radius: 0;\n  background: #0a120c;\n}\n[data-skin=\"terminal\"] .hero-kicker { color: #2bff66; }\n[data-skin=\"terminal\"] .hero-kicker::after {\n  content: \"█\";\n  margin-left: 2px;\n  animation: term-blink 1s steps(1) infinite;\n}\n[data-skin=\"terminal\"] .hero-title { color: #2bff66; }\n[data-skin=\"terminal\"] .hero-sub { color: #36a85a; }\n\n[data-skin=\"terminal\"] .specimen {\n  border: 1px solid var(--border);\n  border-radius: 0;\n  background: #0a120c;\n}\n[data-skin=\"terminal\"] .specimen-head { border-bottom: 1px solid var(--border); background: #0c1c12; }\n[data-skin=\"terminal\"] .specimen-title { color: #2bff66; }\n[data-skin=\"terminal\"] .specimen-title::before { content: \"// \"; color: #36a85a; }\n[data-skin=\"terminal\"] .specimen-tag { color: #36a85a; }\n\n[data-skin=\"terminal\"] .app-status {\n  border: 1px solid var(--border);\n  border-radius: 0;\n  background: #0a120c;\n  color: #36a85a;\n}\n\n/* ---- Controls ----------------------------------------------------------- */\n[data-skin=\"terminal\"] .group\\/button {\n  border: 1px solid #2bff66;\n  border-radius: 0;\n  background: transparent;\n  color: #2bff66;\n  font-weight: 600;\n  box-shadow: none;\n}\n[data-skin=\"terminal\"] .group\\/button::before { content: \"[ \"; }\n[data-skin=\"terminal\"] .group\\/button::after { content: \" ]\"; }\n[data-skin=\"terminal\"] .group\\/button:hover { background: #2bff66; color: #04140a; }\n[data-skin=\"terminal\"] .group\\/button:active:not(:disabled) { background: #1f9f3f; }\n[data-skin=\"terminal\"] .group\\/button:focus-visible { outline: 1px dashed #2bff66; outline-offset: 2px; }\n[data-skin=\"terminal\"] .group\\/button[data-variant=\"default\"] { background: #2bff66; color: #04140a; }\n[data-skin=\"terminal\"] .group\\/button[data-variant=\"destructive\"] { border-color: #ff5f56; color: #ff5f56; }\n[data-skin=\"terminal\"] .group\\/button[data-variant=\"destructive\"]:hover { background: #ff5f56; color: #120404; }\n[data-skin=\"terminal\"] .group\\/button[data-variant=\"link\"] { border: 0; color: #2bff66; text-decoration: underline; }\n[data-skin=\"terminal\"] .group\\/button[data-variant=\"link\"]::before,\n[data-skin=\"terminal\"] .group\\/button[data-variant=\"link\"]::after { content: \"\"; }\n[data-skin=\"terminal\"] .group\\/button[data-variant=\"ghost\"] { border-color: transparent; }\n[data-skin=\"terminal\"] .group\\/button[data-variant=\"ghost\"]:hover { border-color: #2bff66; background: transparent; color: #2bff66; }\n\n[data-skin=\"terminal\"] [data-slot=\"input\"],\n[data-skin=\"terminal\"] [data-slot=\"textarea\"],\n[data-skin=\"terminal\"] [data-slot=\"select-trigger\"],\n[data-skin=\"terminal\"] .skin-select {\n  border: 1px solid var(--border);\n  border-radius: 0;\n  background: #060d08;\n  color: #2bff66;\n  caret-color: #2bff66;\n}\n[data-skin=\"terminal\"] [data-slot=\"input\"]::placeholder,\n[data-skin=\"terminal\"] [data-slot=\"textarea\"]::placeholder { color: #2a7a45; }\n[data-skin=\"terminal\"] [data-slot=\"input\"]:focus-visible,\n[data-skin=\"terminal\"] [data-slot=\"textarea\"]:focus-visible,\n[data-skin=\"terminal\"] [data-slot=\"select-trigger\"]:focus-visible {\n  outline: 0;\n  border-color: #2bff66;\n  box-shadow: 0 0 8px rgba(43, 255, 102, 0.4);\n}\n\n[data-skin=\"terminal\"] [data-slot=\"card\"] { border: 1px solid var(--border); border-radius: 0; background: #0a120c; }\n\n[data-skin=\"terminal\"] [data-slot=\"popover-content\"],\n[data-skin=\"terminal\"] [data-slot=\"dropdown-menu-content\"],\n[data-skin=\"terminal\"] [data-slot=\"context-menu-content\"],\n[data-skin=\"terminal\"] [data-slot=\"select-content\"],\n[data-skin=\"terminal\"] [data-slot=\"command\"],\n[data-skin=\"terminal\"] [data-slot=\"hover-card-content\"] {\n  border: 1px solid #2bff66;\n  border-radius: 0;\n  background: #0a120c;\n  box-shadow: 0 0 14px rgba(43, 255, 102, 0.25);\n}\n[data-skin=\"terminal\"] [data-slot=\"tooltip-content\"] {\n  border: 1px solid #2bff66;\n  border-radius: 0;\n  background: #04140a;\n  color: #2bff66;\n}\n[data-skin=\"terminal\"] [data-slot=\"tooltip-content\"] svg { fill: #04140a; }\n\n[data-skin=\"terminal\"] [data-slot=\"dropdown-menu-item\"][data-highlighted],\n[data-skin=\"terminal\"] [data-slot=\"context-menu-item\"][data-highlighted],\n[data-skin=\"terminal\"] [data-slot=\"select-item\"][data-highlighted],\n[data-skin=\"terminal\"] [data-slot=\"command-item\"][data-selected=\"true\"] {\n  border-radius: 0;\n  background: #2bff66;\n  color: #04140a;\n}\n\n[data-skin=\"terminal\"] [data-slot=\"dialog-content\"],\n[data-skin=\"terminal\"] [data-slot=\"alert-dialog-content\"],\n[data-skin=\"terminal\"] [data-slot=\"sheet-content\"] {\n  border: 1px solid #2bff66;\n  border-radius: 0;\n  background: #0a120c;\n  box-shadow: 0 0 24px rgba(43, 255, 102, 0.3);\n}\n\n[data-skin=\"terminal\"] [data-slot=\"checkbox\"] {\n  border: 1px solid #2bff66;\n  border-radius: 0;\n  background: #060d08;\n  color: #04140a;\n}\n[data-skin=\"terminal\"] [data-slot=\"checkbox\"][data-state=\"checked\"] { background: #2bff66; }\n[data-skin=\"terminal\"] [data-slot=\"radio-group-item\"] {\n  border: 1px solid #2bff66;\n  border-radius: 9999px;\n  background: #060d08;\n  color: #2bff66;\n}\n\n[data-skin=\"terminal\"] [data-slot=\"tabs-list\"] { border-radius: 0; background: transparent; gap: 0; border-bottom: 1px solid var(--border); }\n[data-skin=\"terminal\"] [data-slot=\"tabs-trigger\"] {\n  border: 1px solid var(--border);\n  border-bottom: 0;\n  border-radius: 0;\n  background: #0a120c;\n  color: #36a85a;\n  margin-right: -1px;\n}\n[data-skin=\"terminal\"] [data-slot=\"tabs-trigger\"][data-state=\"active\"] { background: #2bff66; color: #04140a; font-weight: 700; }\n\n[data-skin=\"terminal\"] [data-slot=\"badge\"] { border-radius: 0; border: 1px solid #2bff66; background: transparent; color: #2bff66; }\n[data-skin=\"terminal\"] [data-slot=\"badge\"][data-variant=\"default\"] { background: #2bff66; color: #04140a; }\n\n[data-skin=\"terminal\"] [data-slot=\"switch\"] { border: 1px solid #2bff66; border-radius: 0; background: #060d08; }\n[data-skin=\"terminal\"] [data-slot=\"switch\"] [data-slot=\"switch-thumb\"] { border-radius: 0; background: #2bff66; }\n\n[data-skin=\"terminal\"] [data-slot=\"progress\"] { border: 1px solid var(--border); border-radius: 0; background: #060d08; }\n[data-skin=\"terminal\"] [data-slot=\"progress-indicator\"] { border-radius: 0; background: #2bff66; }\n\n[data-skin=\"terminal\"] [data-slot=\"slider-track\"] { border: 1px solid var(--border); border-radius: 0; background: #060d08; }\n[data-skin=\"terminal\"] [data-slot=\"slider-range\"] { background: #2bff66; }\n[data-skin=\"terminal\"] [data-slot=\"slider-thumb\"] { border: 1px solid #04140a; border-radius: 0; background: #2bff66; box-shadow: 0 0 8px rgba(43,255,102,0.6); }\n\n[data-skin=\"terminal\"] [data-slot=\"alert\"] { border: 1px solid var(--border); border-radius: 0; }\n[data-skin=\"terminal\"] [data-slot=\"table\"] { border: 1px solid var(--border); }\n\n/* Chart: phosphor glow on the bars + dashed grid (layer-3 SVG CSS). Fills come\n   free from the --chart-* tokens above. NOTE: the bar corner-radius is recharts\n   geometry set in JSX (radius={4}); CSS can't flatten it — that's a per-usage\n   prop, not a skin concern. */\n[data-skin=\"terminal\"] [data-slot=\"chart\"] .recharts-bar-rectangle path {\n  filter: drop-shadow(0 0 3px rgba(43, 255, 102, 0.85));\n}\n[data-skin=\"terminal\"] [data-slot=\"chart\"] .recharts-cartesian-grid line {\n  stroke: #1f6f3a;\n  stroke-dasharray: 2 3;\n}\n",
      "type": "registry:file",
      "target": "app/skins/terminal.css"
    }
  ],
  "docs": "1) @import \"./skins/terminal.css\"; in your globals.css.  2) Set data-skin=\"terminal\" on <html>.",
  "type": "registry:item"
}